MANIFEST.in
account_data.xml
setup.py
./__init__.py
./__openerp__.py
i18n/ar.po
i18n/ca.po
i18n/da.po
i18n/en_GB.po
i18n/es.po
i18n/es_CR.po
i18n/es_MX.po
i18n/es_PY.po
i18n/es_VE.po
i18n/gl.po
i18n/it.po
i18n/l10n_th.pot
i18n/nb.po
i18n/nl.po
i18n/pt.po
i18n/pt_BR.po
i18n/sl.po
i18n/sr@latin.po
i18n/th.po
i18n/tr.po
images/config_chart_l10n_th.jpeg
images/l10n_th_chart.jpeg
openerp_l10n_th.egg-info/PKG-INFO
openerp_l10n_th.egg-info/SOURCES.txt
openerp_l10n_th.egg-info/dependency_links.txt
openerp_l10n_th.egg-info/requires.txt
openerp_l10n_th.egg-info/top_level.txt
static/src/img/icon.png